{"config":{"output_file":null,"full_docs":false,"pub_only":true,"reachable_only":true,"distro_crate":false,"signatures":false,"borrow_data":false},"version":"0.19.1","compilation":{"directory":"/Users/julia/.cargo/registry/src/github.com-1ecc6299db9ec823/hmac-drbg-0.2.0","program":"/Users/julia/.rustup/toolchains/stable-x86_64-apple-darwin/bin/rls","arguments":["--crate-name","hmac_drbg","--edition=2018","/Users/julia/.cargo/registry/src/github.com-1ecc6299db9ec823/hmac-drbg-0.2.0/src/lib.rs","--json=diagnostic-rendered-ansi","--crate-type","lib","--emit=dep-info,metadata","-C","embed-bitcode=no","-C","split-debuginfo=unpacked","-C","debuginfo=2","-C","metadata=f984a7d85f47204c","-C","extra-filename=-f984a7d85f47204c","--out-dir","/Users/julia/ruhackathon/target/rls/debug/deps","-L","dependency=/Users/julia/ruhackathon/target/rls/debug/deps","--extern","digest=/Users/julia/ruhackathon/target/rls/debug/deps/libdigest-85e869c072f7816b.rmeta","--extern","generic_array=/Users/julia/ruhackathon/target/rls/debug/deps/libgeneric_array-9ee9f9f02164de32.rmeta","--extern","hmac=/Users/julia/ruhackathon/target/rls/debug/deps/libhmac-b6ffef0da808edb8.rmeta","--cap-lints","allow","--error-format=json","--sysroot","/Users/julia/.rustup/toolchains/stable-x86_64-apple-darwin"],"output":"/Users/julia/ruhackathon/target/rls/debug/deps/libhmac_drbg-f984a7d85f47204c.rmeta"},"prelude":{"crate_id":{"name":"hmac_drbg","disambiguator":[5258003725761777436,13764969738428548317]},"crate_root":"/Users/julia/.cargo/registry/src/github.com-1ecc6299db9ec823/hmac-drbg-0.2.0/src","external_crates":[{"file_name":"/Users/julia/.cargo/registry/src/github.com-1ecc6299db9ec823/hmac-drbg-0.2.0/src/lib.rs","num":1,"id":{"name":"core","disambiguator":[17161976177339802527,9637120080719870273]}},{"file_name":"/Users/julia/.cargo/registry/src/github.com-1ecc6299db9ec823/hmac-drbg-0.2.0/src/lib.rs","num":2,"id":{"name":"compiler_builtins","disambiguator":[12784072134307519025,4657485898025748013]}},{"file_name":"/Users/julia/.cargo/registry/src/github.com-1ecc6299db9ec823/hmac-drbg-0.2.0/src/lib.rs","num":3,"id":{"name":"rustc_std_workspace_core","disambiguator":[8860544973196061204,9932137894390183628]}},{"file_name":"/Users/julia/.cargo/registry/src/github.com-1ecc6299db9ec823/hmac-drbg-0.2.0/src/lib.rs","num":4,"id":{"name":"digest","disambiguator":[16451838057921863342,6531917535652099574]}},{"file_name":"/Users/julia/.cargo/registry/src/github.com-1ecc6299db9ec823/hmac-drbg-0.2.0/src/lib.rs","num":5,"id":{"name":"generic_array","disambiguator":[9261747235224955454,11261499223792740394]}},{"file_name":"/Users/julia/.cargo/registry/src/github.com-1ecc6299db9ec823/hmac-drbg-0.2.0/src/lib.rs","num":6,"id":{"name":"typenum","disambiguator":[14509014512433398701,5747145694384200891]}},{"file_name":"/Users/julia/.cargo/registry/src/github.com-1ecc6299db9ec823/hmac-drbg-0.2.0/src/lib.rs","num":7,"id":{"name":"std","disambiguator":[14497711731351875891,7574154950596153320]}},{"file_name":"/Users/julia/.cargo/registry/src/github.com-1ecc6299db9ec823/hmac-drbg-0.2.0/src/lib.rs","num":8,"id":{"name":"alloc","disambiguator":[15484098214765895148,4360652648143560453]}},{"file_name":"/Users/julia/.cargo/registry/src/github.com-1ecc6299db9ec823/hmac-drbg-0.2.0/src/lib.rs","num":9,"id":{"name":"libc","disambiguator":[13802683045354889200,17279120461159080731]}},{"file_name":"/Users/julia/.cargo/registry/src/github.com-1ecc6299db9ec823/hmac-drbg-0.2.0/src/lib.rs","num":10,"id":{"name":"unwind","disambiguator":[13733846401634403672,16568137600355934567]}},{"file_name":"/Users/julia/.cargo/registry/src/github.com-1ecc6299db9ec823/hmac-drbg-0.2.0/src/lib.rs","num":11,"id":{"name":"cfg_if","disambiguator":[5926527291982439463,7261863668131194074]}},{"file_name":"/Users/julia/.cargo/registry/src/github.com-1ecc6299db9ec823/hmac-drbg-0.2.0/src/lib.rs","num":12,"id":{"name":"hashbrown","disambiguator":[2147386378482378397,1448349958257004752]}},{"file_name":"/Users/julia/.cargo/registry/src/github.com-1ecc6299db9ec823/hmac-drbg-0.2.0/src/lib.rs","num":13,"id":{"name":"rustc_std_workspace_alloc","disambiguator":[8504510625746843556,11549570195915831773]}},{"file_name":"/Users/julia/.cargo/registry/src/github.com-1ecc6299db9ec823/hmac-drbg-0.2.0/src/lib.rs","num":14,"id":{"name":"rustc_demangle","disambiguator":[1145582961014725186,16562354883654090131]}},{"file_name":"/Users/julia/.cargo/registry/src/github.com-1ecc6299db9ec823/hmac-drbg-0.2.0/src/lib.rs","num":15,"id":{"name":"std_detect","disambiguator":[6582153069738696943,14519107576634371424]}},{"file_name":"/Users/julia/.cargo/registry/src/github.com-1ecc6299db9ec823/hmac-drbg-0.2.0/src/lib.rs","num":16,"id":{"name":"addr2line","disambiguator":[15498041504304623936,9266600846380482125]}},{"file_name":"/Users/julia/.cargo/registry/src/github.com-1ecc6299db9ec823/hmac-drbg-0.2.0/src/lib.rs","num":17,"id":{"name":"gimli","disambiguator":[12608136573466536856,1503974727608604885]}},{"file_name":"/Users/julia/.cargo/registry/src/github.com-1ecc6299db9ec823/hmac-drbg-0.2.0/src/lib.rs","num":18,"id":{"name":"object","disambiguator":[16755883997827362908,2889333423780235391]}},{"file_name":"/Users/julia/.cargo/registry/src/github.com-1ecc6299db9ec823/hmac-drbg-0.2.0/src/lib.rs","num":19,"id":{"name":"panic_unwind","disambiguator":[3009561993154964965,13259943199418826037]}},{"file_name":"/Users/julia/.cargo/registry/src/github.com-1ecc6299db9ec823/hmac-drbg-0.2.0/src/lib.rs","num":20,"id":{"name":"hmac","disambiguator":[13533328739647854538,1372252794655313795]}},{"file_name":"/Users/julia/.cargo/registry/src/github.com-1ecc6299db9ec823/hmac-drbg-0.2.0/src/lib.rs","num":21,"id":{"name":"crypto_mac","disambiguator":[6452347978638204634,9110215233553278886]}},{"file_name":"/Users/julia/.cargo/registry/src/github.com-1ecc6299db9ec823/hmac-drbg-0.2.0/src/lib.rs","num":22,"id":{"name":"subtle","disambiguator":[2306907123908344442,2455272380004030000]}}],"span":{"file_name":"/Users/julia/.cargo/registry/src/github.com-1ecc6299db9ec823/hmac-drbg-0.2.0/src/lib.rs","byte_start":0,"byte_end":3177,"line_start":1,"line_end":124,"column_start":1,"column_end":2}},"imports":[],"defs":[{"kind":"Mod","id":{"krate":0,"index":0},"span":{"file_name":"/Users/julia/.cargo/registry/src/github.com-1ecc6299db9ec823/hmac-drbg-0.2.0/src/lib.rs","byte_start":0,"byte_end":3177,"line_start":1,"line_end":124,"column_start":1,"column_end":2},"name":"","qualname":"::","value":"/Users/julia/.cargo/registry/src/github.com-1ecc6299db9ec823/hmac-drbg-0.2.0/src/lib.rs","parent":null,"children":[{"krate":0,"index":1},{"krate":0,"index":2},{"krate":0,"index":3},{"krate":0,"index":4},{"krate":0,"index":5},{"krate":0,"index":8},{"krate":0,"index":11},{"krate":0,"index":14},{"krate":0,"index":17},{"krate":0,"index":18},{"krate":0,"index":21},{"krate":0,"index":24},{"krate":0,"index":25},{"krate":0,"index":28},{"krate":0,"index":31},{"krate":0,"index":36}],"decl_id":null,"docs":"","sig":null,"attributes":[{"value":"no_std","span":{"file_name":"/Users/julia/.cargo/registry/src/github.com-1ecc6299db9ec823/hmac-drbg-0.2.0/src/lib.rs","byte_start":0,"byte_end":10,"line_start":1,"line_end":1,"column_start":1,"column_end":11}}]},{"kind":"Struct","id":{"krate":0,"index":31},"span":{"file_name":"/Users/julia/.cargo/registry/src/github.com-1ecc6299db9ec823/hmac-drbg-0.2.0/src/lib.rs","byte_start":148,"byte_end":156,"line_start":7,"line_end":7,"column_start":12,"column_end":20},"name":"HmacDRBG","qualname":"::HmacDRBG","value":"HmacDRBG {  }","parent":null,"children":[{"krate":0,"index":33},{"krate":0,"index":34},{"krate":0,"index":35}],"decl_id":null,"docs":"","sig":null,"attributes":[]},{"kind":"Method","id":{"krate":0,"index":38},"span":{"file_name":"/Users/julia/.cargo/registry/src/github.com-1ecc6299db9ec823/hmac-drbg-0.2.0/src/lib.rs","byte_start":578,"byte_end":581,"line_start":22,"line_end":22,"column_start":12,"column_end":15},"name":"new","qualname":"<HmacDRBG<D>>::new","value":"pub fn new(&[u8], &[u8], &[u8]) -> Self","parent":null,"children":[],"decl_id":null,"docs":"","sig":null,"attributes":[]},{"kind":"Method","id":{"krate":0,"index":39},"span":{"file_name":"/Users/julia/.cargo/registry/src/github.com-1ecc6299db9ec823/hmac-drbg-0.2.0/src/lib.rs","byte_start":1111,"byte_end":1116,"line_start":45,"line_end":45,"column_start":12,"column_end":17},"name":"count","qualname":"<HmacDRBG<D>>::count","value":"pub fn count(&Self) -> usize","parent":null,"children":[],"decl_id":null,"docs":"","sig":null,"attributes":[]},{"kind":"Method","id":{"krate":0,"index":40},"span":{"file_name":"/Users/julia/.cargo/registry/src/github.com-1ecc6299db9ec823/hmac-drbg-0.2.0/src/lib.rs","byte_start":1172,"byte_end":1178,"line_start":49,"line_end":49,"column_start":12,"column_end":18},"name":"reseed","qualname":"<HmacDRBG<D>>::reseed","value":"pub fn reseed(&mut Self, &[u8], Option<&[u8]>)","parent":null,"children":[],"decl_id":null,"docs":"","sig":null,"attributes":[]},{"kind":"Method","id":{"krate":0,"index":41},"span":{"file_name":"/Users/julia/.cargo/registry/src/github.com-1ecc6299db9ec823/hmac-drbg-0.2.0/src/lib.rs","byte_start":1304,"byte_end":1312,"line_start":53,"line_end":53,"column_start":12,"column_end":20},"name":"generate","qualname":"<HmacDRBG<D>>::generate","value":"pub fn generate<T: ArrayLength<u8>>(&mut Self, Option<&[u8]>)\n-> GenericArray<u8, T>","parent":null,"children":[],"decl_id":null,"docs":"","sig":null,"attributes":[]},{"kind":"Method","id":{"krate":0,"index":43},"span":{"file_name":"/Users/julia/.cargo/registry/src/github.com-1ecc6299db9ec823/hmac-drbg-0.2.0/src/lib.rs","byte_start":1532,"byte_end":1549,"line_start":59,"line_end":59,"column_start":12,"column_end":29},"name":"generate_to_slice","qualname":"<HmacDRBG<D>>::generate_to_slice","value":"pub fn generate_to_slice(&mut Self, &mut [u8], Option<&[u8]>)","parent":null,"children":[],"decl_id":null,"docs":"","sig":null,"attributes":[]}],"impls":[{"id":0,"kind":"Inherent","span":{"file_name":"/Users/julia/.cargo/registry/src/github.com-1ecc6299db9ec823/hmac-drbg-0.2.0/src/lib.rs","byte_start":410,"byte_end":418,"line_start":17,"line_end":17,"column_start":9,"column_end":17},"value":"","parent":null,"children":[{"krate":0,"index":38},{"krate":0,"index":39},{"krate":0,"index":40},{"krate":0,"index":41},{"krate":0,"index":43},{"krate":0,"index":44},{"krate":0,"index":45}],"docs":"","sig":null,"attributes":[]}],"refs":[],"macro_refs":[],"relations":[{"span":{"file_name":"/Users/julia/.cargo/registry/src/github.com-1ecc6299db9ec823/hmac-drbg-0.2.0/src/lib.rs","byte_start":410,"byte_end":418,"line_start":17,"line_end":17,"column_start":9,"column_end":17},"kind":{"Impl":{"id":0}},"from":{"krate":0,"index":31},"to":{"krate":4294967295,"index":4294967295}}]}