{"config":{"output_file":null,"full_docs":false,"pub_only":true,"reachable_only":true,"distro_crate":false,"signatures":false,"borrow_data":false},"version":"0.19.1","compilation":{"directory":"/Users/julia/.cargo/git/checkouts/stronghold.rs-fe28308a6634692d/6dd92dc/utils","program":"/Users/julia/.rustup/toolchains/stable-x86_64-apple-darwin/bin/rls","arguments":["--crate-name","stronghold_utils","--edition=2018","/Users/julia/.cargo/git/checkouts/stronghold.rs-fe28308a6634692d/6dd92dc/utils/src/lib.rs","--json=diagnostic-rendered-ansi","--crate-type","lib","--emit=dep-info,metadata","-C","embed-bitcode=no","-C","split-debuginfo=unpacked","-C","debuginfo=2","-C","metadata=350f2eae558ae2b3","-C","extra-filename=-350f2eae558ae2b3","--out-dir","/Users/julia/ruhackathon/target/rls/debug/deps","-L","dependency=/Users/julia/ruhackathon/target/rls/debug/deps","--extern","futures=/Users/julia/ruhackathon/target/rls/debug/deps/libfutures-ca3da4fd5eb5f5fa.rmeta","--extern","rand=/Users/julia/ruhackathon/target/rls/debug/deps/librand-1fa09ab9ad11226f.rmeta","--extern","riker=/Users/julia/ruhackathon/target/rls/debug/deps/libriker-c57a3a045fcd3eb6.rmeta","--extern","stronghold_derive=/Users/julia/ruhackathon/target/rls/debug/deps/libstronghold_derive-b878be6694ede2c2.dylib","--cap-lints","allow","--error-format=json","--sysroot","/Users/julia/.rustup/toolchains/stable-x86_64-apple-darwin"],"output":"/Users/julia/ruhackathon/target/rls/debug/deps/libstronghold_utils-350f2eae558ae2b3.rmeta"},"prelude":{"crate_id":{"name":"stronghold_utils","disambiguator":[16893523090594328682,12975881831581087154]},"crate_root":"/Users/julia/.cargo/git/checkouts/stronghold.rs-fe28308a6634692d/6dd92dc/utils/src","external_crates":[{"file_name":"/Users/julia/.cargo/git/checkouts/stronghold.rs-fe28308a6634692d/6dd92dc/utils/src/lib.rs","num":1,"id":{"name":"std","disambiguator":[14497711731351875891,7574154950596153320]}},{"file_name":"/Users/julia/.cargo/git/checkouts/stronghold.rs-fe28308a6634692d/6dd92dc/utils/src/lib.rs","num":2,"id":{"name":"core","disambiguator":[17161976177339802527,9637120080719870273]}},{"file_name":"/Users/julia/.cargo/git/checkouts/stronghold.rs-fe28308a6634692d/6dd92dc/utils/src/lib.rs","num":3,"id":{"name":"compiler_builtins","disambiguator":[12784072134307519025,4657485898025748013]}},{"file_name":"/Users/julia/.cargo/git/checkouts/stronghold.rs-fe28308a6634692d/6dd92dc/utils/src/lib.rs","num":4,"id":{"name":"rustc_std_workspace_core","disambiguator":[8860544973196061204,9932137894390183628]}},{"file_name":"/Users/julia/.cargo/git/checkouts/stronghold.rs-fe28308a6634692d/6dd92dc/utils/src/lib.rs","num":5,"id":{"name":"alloc","disambiguator":[15484098214765895148,4360652648143560453]}},{"file_name":"/Users/julia/.cargo/git/checkouts/stronghold.rs-fe28308a6634692d/6dd92dc/utils/src/lib.rs","num":6,"id":{"name":"libc","disambiguator":[13802683045354889200,17279120461159080731]}},{"file_name":"/Users/julia/.cargo/git/checkouts/stronghold.rs-fe28308a6634692d/6dd92dc/utils/src/lib.rs","num":7,"id":{"name":"unwind","disambiguator":[13733846401634403672,16568137600355934567]}},{"file_name":"/Users/julia/.cargo/git/checkouts/stronghold.rs-fe28308a6634692d/6dd92dc/utils/src/lib.rs","num":8,"id":{"name":"cfg_if","disambiguator":[5926527291982439463,7261863668131194074]}},{"file_name":"/Users/julia/.cargo/git/checkouts/stronghold.rs-fe28308a6634692d/6dd92dc/utils/src/lib.rs","num":9,"id":{"name":"hashbrown","disambiguator":[2147386378482378397,1448349958257004752]}},{"file_name":"/Users/julia/.cargo/git/checkouts/stronghold.rs-fe28308a6634692d/6dd92dc/utils/src/lib.rs","num":10,"id":{"name":"rustc_std_workspace_alloc","disambiguator":[8504510625746843556,11549570195915831773]}},{"file_name":"/Users/julia/.cargo/git/checkouts/stronghold.rs-fe28308a6634692d/6dd92dc/utils/src/lib.rs","num":11,"id":{"name":"rustc_demangle","disambiguator":[1145582961014725186,16562354883654090131]}},{"file_name":"/Users/julia/.cargo/git/checkouts/stronghold.rs-fe28308a6634692d/6dd92dc/utils/src/lib.rs","num":12,"id":{"name":"std_detect","disambiguator":[6582153069738696943,14519107576634371424]}},{"file_name":"/Users/julia/.cargo/git/checkouts/stronghold.rs-fe28308a6634692d/6dd92dc/utils/src/lib.rs","num":13,"id":{"name":"addr2line","disambiguator":[15498041504304623936,9266600846380482125]}},{"file_name":"/Users/julia/.cargo/git/checkouts/stronghold.rs-fe28308a6634692d/6dd92dc/utils/src/lib.rs","num":14,"id":{"name":"gimli","disambiguator":[12608136573466536856,1503974727608604885]}},{"file_name":"/Users/julia/.cargo/git/checkouts/stronghold.rs-fe28308a6634692d/6dd92dc/utils/src/lib.rs","num":15,"id":{"name":"object","disambiguator":[16755883997827362908,2889333423780235391]}},{"file_name":"/Users/julia/.cargo/git/checkouts/stronghold.rs-fe28308a6634692d/6dd92dc/utils/src/lib.rs","num":16,"id":{"name":"panic_unwind","disambiguator":[3009561993154964965,13259943199418826037]}},{"file_name":"/Users/julia/.cargo/git/checkouts/stronghold.rs-fe28308a6634692d/6dd92dc/utils/src/ask.rs","num":17,"id":{"name":"riker","disambiguator":[15847179608106536387,2493178242524845882]}},{"file_name":"/Users/julia/.cargo/git/checkouts/stronghold.rs-fe28308a6634692d/6dd92dc/utils/src/ask.rs","num":18,"id":{"name":"regex","disambiguator":[14362150296202606641,17226873482234116236]}},{"file_name":"/Users/julia/.cargo/git/checkouts/stronghold.rs-fe28308a6634692d/6dd92dc/utils/src/ask.rs","num":19,"id":{"name":"regex_syntax","disambiguator":[9850442804862849798,928135895093887]}},{"file_name":"/Users/julia/.cargo/git/checkouts/stronghold.rs-fe28308a6634692d/6dd92dc/utils/src/ask.rs","num":20,"id":{"name":"aho_corasick","disambiguator":[18408067908463936483,1456738894477797208]}},{"file_name":"/Users/julia/.cargo/git/checkouts/stronghold.rs-fe28308a6634692d/6dd92dc/utils/src/ask.rs","num":21,"id":{"name":"memchr","disambiguator":[14986487144500334714,12991395843189082864]}},{"file_name":"/Users/julia/.cargo/git/checkouts/stronghold.rs-fe28308a6634692d/6dd92dc/utils/src/ask.rs","num":22,"id":{"name":"chrono","disambiguator":[6071872422951697765,1966984337164957696]}},{"file_name":"/Users/julia/.cargo/git/checkouts/stronghold.rs-fe28308a6634692d/6dd92dc/utils/src/ask.rs","num":23,"id":{"name":"time","disambiguator":[6106338641632743240,1189832130828986834]}},{"file_name":"/Users/julia/.cargo/git/checkouts/stronghold.rs-fe28308a6634692d/6dd92dc/utils/src/ask.rs","num":24,"id":{"name":"libc","disambiguator":[12590972830871631501,16526445224950325690]}},{"file_name":"/Users/julia/.cargo/git/checkouts/stronghold.rs-fe28308a6634692d/6dd92dc/utils/src/ask.rs","num":25,"id":{"name":"num_integer","disambiguator":[8285904852682821954,1532037240545742252]}},{"file_name":"/Users/julia/.cargo/git/checkouts/stronghold.rs-fe28308a6634692d/6dd92dc/utils/src/ask.rs","num":26,"id":{"name":"num_traits","disambiguator":[13091826814117835981,7718734604099906687]}},{"file_name":"/Users/julia/.cargo/git/checkouts/stronghold.rs-fe28308a6634692d/6dd92dc/utils/src/ask.rs","num":27,"id":{"name":"dashmap","disambiguator":[17727053538493480835,2940128287280189053]}},{"file_name":"/Users/julia/.cargo/git/checkouts/stronghold.rs-fe28308a6634692d/6dd92dc/utils/src/ask.rs","num":28,"id":{"name":"ahash","disambiguator":[13067061122784136819,73318641236251497]}},{"file_name":"/Users/julia/.cargo/git/checkouts/stronghold.rs-fe28308a6634692d/6dd92dc/utils/src/ask.rs","num":29,"id":{"name":"const_random","disambiguator":[715258516034334754,7112549885239283003]}},{"file_name":"/Users/julia/.cargo/git/checkouts/stronghold.rs-fe28308a6634692d/6dd92dc/utils/src/ask.rs","num":30,"id":{"name":"proc_macro_hack","disambiguator":[18271058969028991263,8469930609677089162]}},{"file_name":"/Users/julia/.cargo/git/checkouts/stronghold.rs-fe28308a6634692d/6dd92dc/utils/src/ask.rs","num":31,"id":{"name":"const_random_macro","disambiguator":[10724398994710332569,6782569939348273966]}},{"file_name":"/Users/julia/.cargo/git/checkouts/stronghold.rs-fe28308a6634692d/6dd92dc/utils/src/ask.rs","num":32,"id":{"name":"cfg_if","disambiguator":[2289167216662328546,6201807109160012645]}},{"file_name":"/Users/julia/.cargo/git/checkouts/stronghold.rs-fe28308a6634692d/6dd92dc/utils/src/ask.rs","num":33,"id":{"name":"num_cpus","disambiguator":[8422060596869109656,15717332824689045420]}},{"file_name":"/Users/julia/.cargo/git/checkouts/stronghold.rs-fe28308a6634692d/6dd92dc/utils/src/ask.rs","num":34,"id":{"name":"futures","disambiguator":[1812863278255605029,2770961281455955774]}},{"file_name":"/Users/julia/.cargo/git/checkouts/stronghold.rs-fe28308a6634692d/6dd92dc/utils/src/ask.rs","num":35,"id":{"name":"futures_core","disambiguator":[8468683017787891339,7459186926147353919]}},{"file_name":"/Users/julia/.cargo/git/checkouts/stronghold.rs-fe28308a6634692d/6dd92dc/utils/src/ask.rs","num":36,"id":{"name":"futures_util","disambiguator":[9649981583413311735,8548690671729803383]}},{"file_name":"/Users/julia/.cargo/git/checkouts/stronghold.rs-fe28308a6634692d/6dd92dc/utils/src/ask.rs","num":37,"id":{"name":"pin_utils","disambiguator":[844875656597912059,1290945837348865035]}},{"file_name":"/Users/julia/.cargo/git/checkouts/stronghold.rs-fe28308a6634692d/6dd92dc/utils/src/ask.rs","num":38,"id":{"name":"futures_macro","disambiguator":[9557813062766813589,16123019809660204538]}},{"file_name":"/Users/julia/.cargo/git/checkouts/stronghold.rs-fe28308a6634692d/6dd92dc/utils/src/ask.rs","num":39,"id":{"name":"futures_task","disambiguator":[10381329459361633494,14692669623010626857]}},{"file_name":"/Users/julia/.cargo/git/checkouts/stronghold.rs-fe28308a6634692d/6dd92dc/utils/src/ask.rs","num":40,"id":{"name":"futures_sink","disambiguator":[3440402882736093087,1312079069599411938]}},{"file_name":"/Users/julia/.cargo/git/checkouts/stronghold.rs-fe28308a6634692d/6dd92dc/utils/src/ask.rs","num":41,"id":{"name":"pin_project_lite","disambiguator":[5079589267985904333,13586975437305947899]}},{"file_name":"/Users/julia/.cargo/git/checkouts/stronghold.rs-fe28308a6634692d/6dd92dc/utils/src/ask.rs","num":42,"id":{"name":"futures_channel","disambiguator":[10047542319807341950,9475510133793393252]}},{"file_name":"/Users/julia/.cargo/git/checkouts/stronghold.rs-fe28308a6634692d/6dd92dc/utils/src/ask.rs","num":43,"id":{"name":"slab","disambiguator":[16790178403073099820,8531478558466639940]}},{"file_name":"/Users/julia/.cargo/git/checkouts/stronghold.rs-fe28308a6634692d/6dd92dc/utils/src/ask.rs","num":44,"id":{"name":"futures_io","disambiguator":[10739691845224590613,16739045939891190968]}},{"file_name":"/Users/julia/.cargo/git/checkouts/stronghold.rs-fe28308a6634692d/6dd92dc/utils/src/ask.rs","num":45,"id":{"name":"futures_executor","disambiguator":[15629479933447091678,3622884146080690037]}},{"file_name":"/Users/julia/.cargo/git/checkouts/stronghold.rs-fe28308a6634692d/6dd92dc/utils/src/ask.rs","num":46,"id":{"name":"uuid","disambiguator":[10978907685313597758,11480883712620817215]}},{"file_name":"/Users/julia/.cargo/git/checkouts/stronghold.rs-fe28308a6634692d/6dd92dc/utils/src/ask.rs","num":47,"id":{"name":"serde","disambiguator":[16680636934981297129,6890593759358445311]}},{"file_name":"/Users/julia/.cargo/git/checkouts/stronghold.rs-fe28308a6634692d/6dd92dc/utils/src/ask.rs","num":48,"id":{"name":"serde_derive","disambiguator":[2110390725466229322,3416891245191794241]}},{"file_name":"/Users/julia/.cargo/git/checkouts/stronghold.rs-fe28308a6634692d/6dd92dc/utils/src/ask.rs","num":49,"id":{"name":"getrandom","disambiguator":[17488875655129187426,16701060034023178929]}},{"file_name":"/Users/julia/.cargo/git/checkouts/stronghold.rs-fe28308a6634692d/6dd92dc/utils/src/ask.rs","num":50,"id":{"name":"cfg_if","disambiguator":[6669231008839721604,5451692867657612098]}},{"file_name":"/Users/julia/.cargo/git/checkouts/stronghold.rs-fe28308a6634692d/6dd92dc/utils/src/ask.rs","num":51,"id":{"name":"riker_macros","disambiguator":[429682077775791764,10159820768869085301]}},{"file_name":"/Users/julia/.cargo/git/checkouts/stronghold.rs-fe28308a6634692d/6dd92dc/utils/src/ask.rs","num":52,"id":{"name":"config","disambiguator":[6387302963901244541,8161152012935916969]}},{"file_name":"/Users/julia/.cargo/git/checkouts/stronghold.rs-fe28308a6634692d/6dd92dc/utils/src/ask.rs","num":53,"id":{"name":"nom","disambiguator":[2340020549396818797,7649046548231329676]}},{"file_name":"/Users/julia/.cargo/git/checkouts/stronghold.rs-fe28308a6634692d/6dd92dc/utils/src/ask.rs","num":54,"id":{"name":"lexical_core","disambiguator":[2976958191997760632,9276821855817662341]}},{"file_name":"/Users/julia/.cargo/git/checkouts/stronghold.rs-fe28308a6634692d/6dd92dc/utils/src/ask.rs","num":55,"id":{"name":"arrayvec","disambiguator":[9660255561063938517,2061082229728965424]}},{"file_name":"/Users/julia/.cargo/git/checkouts/stronghold.rs-fe28308a6634692d/6dd92dc/utils/src/ask.rs","num":56,"id":{"name":"static_assertions","disambiguator":[9952482639690939270,12174361566701638983]}},{"file_name":"/Users/julia/.cargo/git/checkouts/stronghold.rs-fe28308a6634692d/6dd92dc/utils/src/ask.rs","num":57,"id":{"name":"ryu","disambiguator":[1414442814882747122,12094744306941252496]}},{"file_name":"/Users/julia/.cargo/git/checkouts/stronghold.rs-fe28308a6634692d/6dd92dc/utils/src/ask.rs","num":58,"id":{"name":"bitflags","disambiguator":[12623330899898640651,14695839075394095614]}},{"file_name":"/Users/julia/.cargo/git/checkouts/stronghold.rs-fe28308a6634692d/6dd92dc/utils/src/ask.rs","num":59,"id":{"name":"lazy_static","disambiguator":[15857464307233327955,12673070780741664979]}},{"file_name":"/Users/julia/.cargo/git/checkouts/stronghold.rs-fe28308a6634692d/6dd92dc/utils/src/ask.rs","num":60,"id":{"name":"spin","disambiguator":[3712400808281976182,13928776791365620516]}},{"file_name":"/Users/julia/.cargo/git/checkouts/stronghold.rs-fe28308a6634692d/6dd92dc/utils/src/ask.rs","num":61,"id":{"name":"toml","disambiguator":[3581402386128227425,857893402504223659]}},{"file_name":"/Users/julia/.cargo/git/checkouts/stronghold.rs-fe28308a6634692d/6dd92dc/utils/src/ask.rs","num":62,"id":{"name":"serde_json","disambiguator":[7367540479330758090,461710032039532693]}},{"file_name":"/Users/julia/.cargo/git/checkouts/stronghold.rs-fe28308a6634692d/6dd92dc/utils/src/ask.rs","num":63,"id":{"name":"indexmap","disambiguator":[13066200768255387230,370401338510757639]}},{"file_name":"/Users/julia/.cargo/git/checkouts/stronghold.rs-fe28308a6634692d/6dd92dc/utils/src/ask.rs","num":64,"id":{"name":"hashbrown","disambiguator":[15372693092134288842,5723280804133582129]}},{"file_name":"/Users/julia/.cargo/git/checkouts/stronghold.rs-fe28308a6634692d/6dd92dc/utils/src/ask.rs","num":65,"id":{"name":"ahash","disambiguator":[11689723616671681335,3400359134906406193]}},{"file_name":"/Users/julia/.cargo/git/checkouts/stronghold.rs-fe28308a6634692d/6dd92dc/utils/src/ask.rs","num":66,"id":{"name":"itoa","disambiguator":[4053364750128791569,17849697835791693943]}},{"file_name":"/Users/julia/.cargo/git/checkouts/stronghold.rs-fe28308a6634692d/6dd92dc/utils/src/ask.rs","num":67,"id":{"name":"yaml_rust","disambiguator":[15880352148357885750,16823526773768642330]}},{"file_name":"/Users/julia/.cargo/git/checkouts/stronghold.rs-fe28308a6634692d/6dd92dc/utils/src/ask.rs","num":68,"id":{"name":"linked_hash_map","disambiguator":[923132072555163228,10045294568001605436]}},{"file_name":"/Users/julia/.cargo/git/checkouts/stronghold.rs-fe28308a6634692d/6dd92dc/utils/src/ask.rs","num":69,"id":{"name":"serde_hjson","disambiguator":[3471714373059747664,13436260228451354102]}},{"file_name":"/Users/julia/.cargo/git/checkouts/stronghold.rs-fe28308a6634692d/6dd92dc/utils/src/ask.rs","num":70,"id":{"name":"linked_hash_map","disambiguator":[14772054550093027702,13659313428513205599]}},{"file_name":"/Users/julia/.cargo/git/checkouts/stronghold.rs-fe28308a6634692d/6dd92dc/utils/src/ask.rs","num":71,"id":{"name":"serde","disambiguator":[5803674997380607131,216596507539999362]}},{"file_name":"/Users/julia/.cargo/git/checkouts/stronghold.rs-fe28308a6634692d/6dd92dc/utils/src/ask.rs","num":72,"id":{"name":"num_traits","disambiguator":[8706843723519832556,3565254973075826981]}},{"file_name":"/Users/julia/.cargo/git/checkouts/stronghold.rs-fe28308a6634692d/6dd92dc/utils/src/ask.rs","num":73,"id":{"name":"ini","disambiguator":[12711482842145947689,7186268757076377145]}},{"file_name":"/Users/julia/.cargo/git/checkouts/stronghold.rs-fe28308a6634692d/6dd92dc/utils/src/ask.rs","num":74,"id":{"name":"slog","disambiguator":[1209115503992851491,12891711989846275931]}},{"file_name":"/Users/julia/.cargo/git/checkouts/stronghold.rs-fe28308a6634692d/6dd92dc/utils/src/ask.rs","num":75,"id":{"name":"rand","disambiguator":[5333419417851938570,7763815584343642162]}},{"file_name":"/Users/julia/.cargo/git/checkouts/stronghold.rs-fe28308a6634692d/6dd92dc/utils/src/ask.rs","num":76,"id":{"name":"rand_core","disambiguator":[3071514816907896073,4995051925669756056]}},{"file_name":"/Users/julia/.cargo/git/checkouts/stronghold.rs-fe28308a6634692d/6dd92dc/utils/src/ask.rs","num":77,"id":{"name":"getrandom","disambiguator":[547646230474901612,13922360578777660980]}},{"file_name":"/Users/julia/.cargo/git/checkouts/stronghold.rs-fe28308a6634692d/6dd92dc/utils/src/ask.rs","num":78,"id":{"name":"rand_chacha","disambiguator":[15361780465377974707,14430483732473828897]}},{"file_name":"/Users/julia/.cargo/git/checkouts/stronghold.rs-fe28308a6634692d/6dd92dc/utils/src/ask.rs","num":79,"id":{"name":"ppv_lite86","disambiguator":[45222660997085021,10036847386984840147]}},{"file_name":"/Users/julia/.cargo/git/checkouts/stronghold.rs-fe28308a6634692d/6dd92dc/utils/src/ask.rs","num":80,"id":{"name":"slog_scope","disambiguator":[7958449358286935577,13780251399191804380]}},{"file_name":"/Users/julia/.cargo/git/checkouts/stronghold.rs-fe28308a6634692d/6dd92dc/utils/src/ask.rs","num":81,"id":{"name":"arc_swap","disambiguator":[6999955856352368926,15584443582164284231]}},{"file_name":"/Users/julia/.cargo/git/checkouts/stronghold.rs-fe28308a6634692d/6dd92dc/utils/src/ask.rs","num":82,"id":{"name":"slog_stdlog","disambiguator":[16162042729633339928,817333007299133653]}},{"file_name":"/Users/julia/.cargo/git/checkouts/stronghold.rs-fe28308a6634692d/6dd92dc/utils/src/ask.rs","num":83,"id":{"name":"log","disambiguator":[18215375064022211296,6473788141846969994]}},{"file_name":"/Users/julia/.cargo/git/checkouts/stronghold.rs-fe28308a6634692d/6dd92dc/utils/src/lib.rs","num":84,"id":{"name":"stronghold_derive","disambiguator":[424165592533321569,15427201134650477475]}},{"file_name":"/Users/julia/.cargo/git/checkouts/stronghold.rs-fe28308a6634692d/6dd92dc/utils/src/test_utils/fresh.rs","num":85,"id":{"name":"rand","disambiguator":[6413201693484654836,1060022797653377114]}},{"file_name":"/Users/julia/.cargo/git/checkouts/stronghold.rs-fe28308a6634692d/6dd92dc/utils/src/test_utils/fresh.rs","num":86,"id":{"name":"rand_core","disambiguator":[11887644693504216196,7259550397967195635]}},{"file_name":"/Users/julia/.cargo/git/checkouts/stronghold.rs-fe28308a6634692d/6dd92dc/utils/src/test_utils/fresh.rs","num":87,"id":{"name":"rand_chacha","disambiguator":[11848882135860767570,903087901216273526]}}],"span":{"file_name":"/Users/julia/.cargo/git/checkouts/stronghold.rs-fe28308a6634692d/6dd92dc/utils/src/lib.rs","byte_start":77,"byte_end":184,"line_start":4,"line_end":7,"column_start":1,"column_end":61}},"imports":[{"kind":"Use","ref_id":{"krate":0,"index":26},"span":{"file_name":"/Users/julia/.cargo/git/checkouts/stronghold.rs-fe28308a6634692d/6dd92dc/utils/src/lib.rs","byte_start":119,"byte_end":122,"line_start":6,"line_end":6,"column_start":14,"column_end":17},"alias_span":null,"name":"ask","value":"","parent":{"krate":0,"index":0}},{"kind":"Use","ref_id":{"krate":84,"index":54},"span":{"file_name":"/Users/julia/.cargo/git/checkouts/stronghold.rs-fe28308a6634692d/6dd92dc/utils/src/lib.rs","byte_start":152,"byte_end":162,"line_start":7,"line_end":7,"column_start":29,"column_end":39},"alias_span":null,"name":"GuardDebug","value":"","parent":{"krate":0,"index":0}},{"kind":"Use","ref_id":{"krate":84,"index":55},"span":{"file_name":"/Users/julia/.cargo/git/checkouts/stronghold.rs-fe28308a6634692d/6dd92dc/utils/src/lib.rs","byte_start":164,"byte_end":182,"line_start":7,"line_end":7,"column_start":41,"column_end":59},"alias_span":null,"name":"RequestPermissions","value":"","parent":{"krate":0,"index":0}}],"defs":[{"kind":"Mod","id":{"krate":0,"index":0},"span":{"file_name":"/Users/julia/.cargo/git/checkouts/stronghold.rs-fe28308a6634692d/6dd92dc/utils/src/lib.rs","byte_start":77,"byte_end":184,"line_start":4,"line_end":7,"column_start":1,"column_end":61},"name":"","qualname":"::","value":"/Users/julia/.cargo/git/checkouts/stronghold.rs-fe28308a6634692d/6dd92dc/utils/src/lib.rs","parent":null,"children":[{"krate":0,"index":1},{"krate":0,"index":2},{"krate":0,"index":3},{"krate":0,"index":42},{"krate":0,"index":77},{"krate":0,"index":80},{"krate":0,"index":81},{"krate":0,"index":84}],"decl_id":null,"docs":"","sig":null,"attributes":[]},{"kind":"Function","id":{"krate":0,"index":26},"span":{"file_name":"/Users/julia/.cargo/git/checkouts/stronghold.rs-fe28308a6634692d/6dd92dc/utils/src/ask.rs","byte_start":462,"byte_end":465,"line_start":15,"line_end":15,"column_start":8,"column_end":11},"name":"ask","qualname":"::ask::ask","value":"pub fn ask<Msg, Ctx, R, T>(&Ctx, &T, Msg) -> RemoteHandle<R> where\nMsg: Message, R: Message, Ctx: TmpActorRefFactory + Run, T: Tell<Msg>","parent":null,"children":[],"decl_id":null,"docs":"","sig":null,"attributes":[]},{"kind":"Mod","id":{"krate":0,"index":42},"span":{"file_name":"/Users/julia/.cargo/git/checkouts/stronghold.rs-fe28308a6634692d/6dd92dc/utils/src/test_utils/mod.rs","byte_start":0,"byte_end":0,"line_start":1,"line_end":1,"column_start":1,"column_end":1},"name":"test_utils","qualname":"::test_utils","value":"/Users/julia/.cargo/git/checkouts/stronghold.rs-fe28308a6634692d/6dd92dc/utils/src/test_utils/mod.rs","parent":null,"children":[{"krate":0,"index":43},{"krate":0,"index":44},{"krate":0,"index":45},{"krate":0,"index":48},{"krate":0,"index":51},{"krate":0,"index":52},{"krate":0,"index":55},{"krate":0,"index":58},{"krate":0,"index":61},{"krate":0,"index":64},{"krate":0,"index":67},{"krate":0,"index":73},{"krate":0,"index":74},{"krate":0,"index":75},{"krate":0,"index":76}],"decl_id":null,"docs":"","sig":null,"attributes":[]},{"kind":"Mod","id":{"krate":0,"index":67},"span":{"file_name":"/Users/julia/.cargo/git/checkouts/stronghold.rs-fe28308a6634692d/6dd92dc/utils/src/test_utils/fresh.rs","byte_start":0,"byte_end":0,"line_start":1,"line_end":1,"column_start":1,"column_end":1},"name":"fresh","qualname":"::test_utils::fresh","value":"/Users/julia/.cargo/git/checkouts/stronghold.rs-fe28308a6634692d/6dd92dc/utils/src/test_utils/fresh.rs","parent":null,"children":[{"krate":0,"index":68},{"krate":0,"index":69},{"krate":0,"index":70},{"krate":0,"index":71},{"krate":0,"index":72}],"decl_id":null,"docs":"","sig":null,"attributes":[]},{"kind":"Function","id":{"krate":0,"index":68},"span":{"file_name":"/Users/julia/.cargo/git/checkouts/stronghold.rs-fe28308a6634692d/6dd92dc/utils/src/test_utils/fresh.rs","byte_start":2470,"byte_end":2480,"line_start":4,"line_end":4,"column_start":8,"column_end":18},"name":"bytestring","qualname":"::test_utils::fresh::bytestring","value":"pub fn bytestring() -> Vec<u8>","parent":null,"children":[],"decl_id":null,"docs":"","sig":null,"attributes":[]},{"kind":"Function","id":{"krate":0,"index":69},"span":{"file_name":"/Users/julia/.cargo/git/checkouts/stronghold.rs-fe28308a6634692d/6dd92dc/utils/src/test_utils/fresh.rs","byte_start":2729,"byte_end":2749,"line_start":18,"line_end":18,"column_start":8,"column_end":28},"name":"non_empty_bytestring","qualname":"::test_utils::fresh::non_empty_bytestring","value":"pub fn non_empty_bytestring() -> Vec<u8>","parent":null,"children":[],"decl_id":null,"docs":"","sig":null,"attributes":[]},{"kind":"Function","id":{"krate":0,"index":70},"span":{"file_name":"/Users/julia/.cargo/git/checkouts/stronghold.rs-fe28308a6634692d/6dd92dc/utils/src/test_utils/fresh.rs","byte_start":2931,"byte_end":2937,"line_start":27,"line_end":27,"column_start":8,"column_end":14},"name":"string","qualname":"::test_utils::fresh::string","value":"pub fn string() -> String","parent":null,"children":[],"decl_id":null,"docs":"","sig":null,"attributes":[]},{"kind":"Function","id":{"krate":0,"index":71},"span":{"file_name":"/Users/julia/.cargo/git/checkouts/stronghold.rs-fe28308a6634692d/6dd92dc/utils/src/test_utils/fresh.rs","byte_start":3184,"byte_end":3192,"line_start":41,"line_end":41,"column_start":8,"column_end":16},"name":"coinflip","qualname":"::test_utils::fresh::coinflip","value":"pub fn coinflip() -> bool","parent":null,"children":[],"decl_id":null,"docs":"","sig":null,"attributes":[]},{"kind":"Function","id":{"krate":0,"index":72},"span":{"file_name":"/Users/julia/.cargo/git/checkouts/stronghold.rs-fe28308a6634692d/6dd92dc/utils/src/test_utils/fresh.rs","byte_start":3234,"byte_end":3239,"line_start":45,"line_end":45,"column_start":8,"column_end":13},"name":"usize","qualname":"::test_utils::fresh::usize","value":"pub fn usize(usize) -> usize","parent":null,"children":[],"decl_id":null,"docs":"","sig":null,"attributes":[]},{"kind":"Function","id":{"krate":0,"index":73},"span":{"file_name":"/Users/julia/.cargo/git/checkouts/stronghold.rs-fe28308a6634692d/6dd92dc/utils/src/test_utils/mod.rs","byte_start":1658,"byte_end":1665,"line_start":12,"line_end":12,"column_start":8,"column_end":15},"name":"corrupt","qualname":"::test_utils::corrupt","value":"pub fn corrupt(&mut [u8])","parent":null,"children":[],"decl_id":null,"docs":"","sig":null,"attributes":[]},{"kind":"Function","id":{"krate":0,"index":75},"span":{"file_name":"/Users/julia/.cargo/git/checkouts/stronghold.rs-fe28308a6634692d/6dd92dc/utils/src/test_utils/mod.rs","byte_start":2014,"byte_end":2026,"line_start":30,"line_end":30,"column_start":8,"column_end":20},"name":"corrupt_file","qualname":"::test_utils::corrupt_file","value":"pub fn corrupt_file(&mut File)","parent":null,"children":[],"decl_id":null,"docs":"","sig":null,"attributes":[]},{"kind":"Function","id":{"krate":0,"index":76},"span":{"file_name":"/Users/julia/.cargo/git/checkouts/stronghold.rs-fe28308a6634692d/6dd92dc/utils/src/test_utils/mod.rs","byte_start":2253,"byte_end":2268,"line_start":43,"line_end":43,"column_start":8,"column_end":23},"name":"corrupt_file_at","qualname":"::test_utils::corrupt_file_at","value":"pub fn corrupt_file_at(&Path)","parent":null,"children":[],"decl_id":null,"docs":"","sig":null,"attributes":[]}],"impls":[{"id":0,"kind":"Inherent","span":{"file_name":"/Users/julia/.cargo/git/checkouts/stronghold.rs-fe28308a6634692d/6dd92dc/utils/src/ask.rs","byte_start":1023,"byte_end":1031,"line_start":36,"line_end":36,"column_start":20,"column_end":28},"value":"","parent":null,"children":[{"krate":0,"index":37}],"docs":"","sig":null,"attributes":[]},{"id":1,"kind":"Direct","span":{"file_name":"/Users/julia/.cargo/git/checkouts/stronghold.rs-fe28308a6634692d/6dd92dc/utils/src/ask.rs","byte_start":1210,"byte_end":1218,"line_start":43,"line_end":43,"column_start":30,"column_end":38},"value":"","parent":null,"children":[{"krate":0,"index":40},{"krate":0,"index":41}],"docs":"","sig":null,"attributes":[]}],"refs":[{"kind":"Mod","span":{"file_name":"/Users/julia/.cargo/git/checkouts/stronghold.rs-fe28308a6634692d/6dd92dc/utils/src/lib.rs","byte_start":94,"byte_end":104,"line_start":5,"line_end":5,"column_start":9,"column_end":19},"ref_id":{"krate":0,"index":42}},{"kind":"Mod","span":{"file_name":"/Users/julia/.cargo/git/checkouts/stronghold.rs-fe28308a6634692d/6dd92dc/utils/src/test_utils/mod.rs","byte_start":1643,"byte_end":1648,"line_start":10,"line_end":10,"column_start":9,"column_end":14},"ref_id":{"krate":0,"index":67}}],"macro_refs":[],"relations":[{"span":{"file_name":"/Users/julia/.cargo/git/checkouts/stronghold.rs-fe28308a6634692d/6dd92dc/utils/src/ask.rs","byte_start":1023,"byte_end":1031,"line_start":36,"line_end":36,"column_start":20,"column_end":28},"kind":{"Impl":{"id":0}},"from":{"krate":0,"index":32},"to":{"krate":4294967295,"index":4294967295}},{"span":{"file_name":"/Users/julia/.cargo/git/checkouts/stronghold.rs-fe28308a6634692d/6dd92dc/utils/src/ask.rs","byte_start":1210,"byte_end":1218,"line_start":43,"line_end":43,"column_start":30,"column_end":38},"kind":{"Impl":{"id":1}},"from":{"krate":0,"index":32},"to":{"krate":17,"index":990}}]}